pyfwc/__init__.py
pyfwc/__version__.py
pyfwc/fwc.py
pyfwc-0.3.0.dist-info/LICENSE
pyfwc-0.3.0.dist-info/METADATA
pyfwc-0.3.0.dist-info/WHEEL
pyfwc-0.3.0.dist-info/top_level.txt
pyfwc-0.3.0.dist-info/RECORD
