Metadata-Version: 2.1
Name: pyfwc
Version: 0.3.0
Summary: Python wrapper for Australian Fair Work Commission API
Home-page: https://github.com/frankzhangsyd/pyfwc
Author: Frank Zhang
Author-email: frank.dingrui@gmail.com
License: MIT
Classifier: License :: OSI Approved :: MIT License
Classifier: Programming Language :: Python
Classifier: Programming Language :: Python :: 3
Classifier: Programming Language :: Python :: 3.6
Classifier: Programming Language :: Python :: Implementation :: CPython
Classifier: Programming Language :: Python :: Implementation :: PyPy
Requires-Python: >=3.7.4
License-File: LICENSE
Requires-Dist: requests >=2.26.0
Requires-Dist: pandas >=1.3.4
